{"schemaVersion":2,"mediaType":"application/vnd.oci.image.manifest.v1+json","config":{"mediaType":"application/vnd.oci.image.config.v1+json","digest":"sha256:6a4c1012810436996f985e61b11d6e7838afd7de7fa42be7e79ff97c2cf29409","size":305},"layers":[{"mediaType":"application/vnd.oci.image.layer.v1.tar","digest":"sha256:8563955ab1639ffde87b246459e06fcdfa030ba35a3fae8b3c9bcdc8cafbc36e","size":20480}],"annotations":{"org.opencontainers.image.url":"https://hub.docker.com/_/hello-world","org.opencontainers.image.version":"linux"}}